Find_Sitemap/__init__.py
Find_Sitemap/main.py
Find_Sitemap/tag.py
tasks/__init__.py
tasks/build.py
tasks/common.py
tasks/doc.py
tasks/env.py
tasks/git.py
tasks/secure.py
tasks/style.py
tasks/test.py
tests/__init__.py
tests/test_Find-Sitemaps.py
Find_Sitemap-0.1.4.dist-info/LICENSE
Find_Sitemap-0.1.4.dist-info/METADATA
Find_Sitemap-0.1.4.dist-info/WHEEL
Find_Sitemap-0.1.4.dist-info/top_level.txt
Find_Sitemap-0.1.4.dist-info/RECORD
